odoo/addons/purchase_stock_manual_currency/README.rst
odoo/addons/purchase_stock_manual_currency/__init__.py
odoo/addons/purchase_stock_manual_currency/__manifest__.py
odoo/addons/purchase_stock_manual_currency/i18n/it.po
odoo/addons/purchase_stock_manual_currency/i18n/purchase_stock_manual_currency.pot
odoo/addons/purchase_stock_manual_currency/models/__init__.py
odoo/addons/purchase_stock_manual_currency/models/stock_move.py
odoo/addons/purchase_stock_manual_currency/readme/CONTRIBUTORS.md
odoo/addons/purchase_stock_manual_currency/readme/DESCRIPTION.md
odoo/addons/purchase_stock_manual_currency/static/description/icon.png
odoo/addons/purchase_stock_manual_currency/static/description/index.html
odoo/addons/purchase_stock_manual_currency/tests/__init__.py
odoo/addons/purchase_stock_manual_currency/tests/test_purchase_stock_manual_currency.py
odoo_addon_purchase_stock_manual_currency-18.0.1.0.0.4.dist-info/METADATA
odoo_addon_purchase_stock_manual_currency-18.0.1.0.0.4.dist-info/WHEEL
odoo_addon_purchase_stock_manual_currency-18.0.1.0.0.4.dist-info/top_level.txt
odoo_addon_purchase_stock_manual_currency-18.0.1.0.0.4.dist-info/RECORD
